lighthousellmm/__init__.py
lighthousellmm/_expect.py
lighthousellmm/_internal/__init__.py
lighthousellmm/_internal/_aiter.py
lighthousellmm/_internal/_background_thread.py
lighthousellmm/_internal/_beta_decorator.py
lighthousellmm/_internal/_compressed_traces.py
lighthousellmm/_internal/_constants.py
lighthousellmm/_internal/_edit_distance.py
lighthousellmm/_internal/_embedding_distance.py
lighthousellmm/_internal/_multipart.py
lighthousellmm/_internal/_operations.py
lighthousellmm/_internal/_orjson.py
lighthousellmm/_internal/_patch.py
lighthousellmm/_internal/_serde.py
lighthousellmm/anonymizer.py
lighthousellmm/async_client.py
lighthousellmm/beta/__init__.py
lighthousellmm/beta/_evals.py
lighthousellmm/cli/README.md
lighthousellmm/client.py
lighthousellmm/env/__init__.py
lighthousellmm/env/_git.py
lighthousellmm/env/_runtime_env.py
lighthousellmm/evaluation/__init__.py
lighthousellmm/evaluation/_arunner.py
lighthousellmm/evaluation/_name_generation.py
lighthousellmm/evaluation/_runner.py
lighthousellmm/evaluation/evaluator.py
lighthousellmm/evaluation/integrations/__init__.py
lighthousellmm/evaluation/integrations/_langchain.py
lighthousellmm/evaluation/integrations/test.excalidraw.png
lighthousellmm/evaluation/llm_evaluator.py
lighthousellmm/evaluation/string_evaluator.py
lighthousellmm/middleware.py
lighthousellmm/py.typed
lighthousellmm/pytest_plugin.py
lighthousellmm/run_helpers.py
lighthousellmm/run_trees.py
lighthousellmm/schemas.py
lighthousellmm/testing/__init__.py
lighthousellmm/testing/_internal.py
lighthousellmm/utils.py
lighthousellmm/wrappers/__init__.py
lighthousellmm/wrappers/_anthropic.py
lighthousellmm/wrappers/_openai.py
lighthousellmm-0.3.14.dist-info/entry_points.txt
lighthousellmm-0.3.14.dist-info/METADATA
lighthousellmm-0.3.14.dist-info/WHEEL
lighthousellmm-0.3.14.dist-info/RECORD
